README.rst
setup.py
twitter2rss.py
twitter2rss.egg-info/PKG-INFO
twitter2rss.egg-info/SOURCES.txt
twitter2rss.egg-info/dependency_links.txt
twitter2rss.egg-info/requires.txt
twitter2rss.egg-info/top_level.txt