Metadata-Version: 1.1
Name: twitter2rss
Version: 0.2.1.3
Summary: Parse Twitter users and create RSS files
Home-page: http://daemons.cf/cgit/twiter2rss/about/
Author: drymer
Author-email: drymer@autistici.org
License: GPLv3
Platform: UNKNOWN
Classifier: Development Status :: 4 - Beta
Classifier: Programming Language :: Python
Classifier: Programming Language :: Python :: 3
Classifier: Programming Language :: Python :: 3.4
Classifier: Operating System :: OS Independent
Classifier: Operating System :: POSIX
Classifier: Intended Audience :: End Users/Desktop
